fsd/FirstPromptAgent.py
fsd/ResultsManager.py
fsd/ResultsManager1.py
fsd/__init__.py
fsd/main.py
fsd/MainOperation/FilesCompiler.py
fsd/MainOperation/MainBuilderAgent.py
fsd/MainOperation/ProjectManager.py
fsd/MainOperation/ProjectsRunner.py
fsd/MainOperation/__init__.py
fsd/Scanner1/DependenciesFinderAgent.py
fsd/Scanner1/DependencyAgent.py
fsd/Scanner1/ProjectScanner1.py
fsd/Scanner1/ScannerAgent.py
fsd/Scanner1/__init__.py
fsd/coding_agent/BugExplainer.py
fsd/coding_agent/BugExplorer.py
fsd/coding_agent/CodingAgent.py
fsd/coding_agent/ControllerAgent.py
fsd/coding_agent/FileFinderAgent.py
fsd/coding_agent/FileLightWorkingAgent.py
fsd/coding_agent/FileManagerAgent.py
fsd/coding_agent/FormattingAgent.py
fsd/coding_agent/IdeaDevelopment.py
fsd/coding_agent/LanguageAgent.py
fsd/coding_agent/LightCodeAgent.py
fsd/coding_agent/PrePromptAgent.py
fsd/coding_agent/SelfHealingAgent.py
fsd/coding_agent/TechStackAgent.py
fsd/coding_agent/TechnicalExplainerAgent.py
fsd/coding_agent/__init__.py
fsd/explainer/ExplainableFileFinderAgent.py
fsd/explainer/ExplainablePrePromptAgent.py
fsd/explainer/ExplainerController.py
fsd/explainer/GeneralExplainerAgent.py
fsd/explainer/MainExplainerAgent.py
fsd/explainer/__init__.py
fsd/log/custom_format.py
fsd/log/logger_config.py
fsd/scanner/ImageScanner.py
fsd/scanner/InfoPlistScanner.py
fsd/scanner/NibScanner.py
fsd/scanner/ObjectiveCScanner.py
fsd/scanner/PlistScanner.py
fsd/scanner/ProjectScanner.py
fsd/scanner/StoryboardScanner.py
fsd/scanner/SwiftScanner.py
fsd/scanner/XibScanner.py
fsd/scanner/__init__.py
fsd/scanner/base64encoder.py
fsd/scanner/overallProjectScanner.py
fsd/util/__init__.py
fsd/util/astparser.py
fsd/util/portkey.py
fsd/util/tree.py
fsd/util/utils.py
zinley_fsd-0.0.1.dist-info/METADATA
zinley_fsd-0.0.1.dist-info/WHEEL
zinley_fsd-0.0.1.dist-info/top_level.txt
zinley_fsd-0.0.1.dist-info/RECORD
