Metadata-Version: 2.1
Name: zinley-fsd
Version: 0.0.1
Summary: A brief description of your library
Home-page: https://github.com/Zinley-dev/fsd_v2_universal
Author: Zinley
Author-email: dev@zinley.com
Classifier: Programming Language :: Python :: 3
Classifier: License :: OSI Approved :: MIT License
Classifier: Operating System :: OS Independent
Requires-Python: >=3.6
Requires-Dist: aiohttp ==3.9.5
Requires-Dist: aiosignal ==1.3.1
Requires-Dist: attrs ==23.2.0
Requires-Dist: cairocffi ==1.7.1
Requires-Dist: CairoSVG ==2.7.1
Requires-Dist: certifi ==2024.7.4
Requires-Dist: cffi ==1.16.0
Requires-Dist: charset-normalizer ==3.3.2
Requires-Dist: cssselect2 ==0.7.0
Requires-Dist: defusedxml ==0.7.1
Requires-Dist: docopt ==0.6.2
Requires-Dist: frozenlist ==1.4.1
Requires-Dist: idna ==3.7
Requires-Dist: multidict ==6.0.5
Requires-Dist: openstep-parser ==1.5.4
Requires-Dist: pbxproj ==4.2.0
Requires-Dist: pillow ==10.4.0
Requires-Dist: portkey-ai ==1.8.3
Requires-Dist: pycparser ==2.22
Requires-Dist: requests ==2.32.3
Requires-Dist: tinycss2 ==1.3.0
Requires-Dist: urllib3 ==2.2.2
Requires-Dist: webencodings ==0.5.1
Requires-Dist: yarl ==1.9.4
Requires-Dist: json-repair ==0.25.3
Requires-Dist: setuptools ==73.0.1
